{"residence":"6745 Del Playa Dr, Goleta CA 93117","routers":[{"mac_address":"0000:0000:0000:0000","serial_number":"12345678","router_model":"SR400ac","name":"name","latitude":34.40949267564314,"longitude":-119.86455872654915}],"heatmap":{"channel":"","radio":"","heatmap_points":[{"latitude":34.40940305412643,"longitude":-119.86457884311676,"client_info":"","upstream_bps":48.2825,"downstream_bps":48.373999999999995,"jitter":38927,"client_rssi":-65,"router_rssi":0,"num_active_clients":1,"client_tx_speed":0,"client_rx_speed":0,"client_tx_retries":0,"client_rx_retries":0,"retransmits":7,"lost_percent":0}]}}